adapt/__init__.py
adapt/context.py
adapt/engine.py
adapt/entity_tagger.py
adapt/expander.py
adapt/intent.py
adapt/parser.py
adapt/tools/__init__.py
adapt/tools/debug/__init__.py
adapt/tools/text/__init__.py
adapt/tools/text/tokenizer.py
adapt/tools/text/trie.py
adapt_parser-0.6.2.dist-info/LICENSE.md
adapt_parser-0.6.2.dist-info/METADATA
adapt_parser-0.6.2.dist-info/WHEEL
adapt_parser-0.6.2.dist-info/top_level.txt
adapt_parser-0.6.2.dist-info/RECORD
