Metadata-Version: 2.1
Name: adapt-parser
Version: 0.6.2
Summary: A text-to-intent parsing framework.
Home-page: https://github.com/MycroftAI/adapt
Author: Sean Fitzgerald
Author-email: sean@fitzgeralds.me
License: Apache License 2.0
Keywords: natural language processing
Platform: UNKNOWN
Classifier: Development Status :: 4 - Beta
Classifier: Intended Audience :: Developers
Classifier: Topic :: Text Processing :: Linguistic
Classifier: License :: OSI Approved :: Apache Software License
Classifier: Programming Language :: Python :: 2.7
Classifier: Programming Language :: Python :: 3.5
Classifier: Programming Language :: Python :: 3.6
Classifier: Programming Language :: Python :: 3.7
Classifier: Programming Language :: Python :: 3.8
Classifier: Programming Language :: Python :: 3.9
Requires-Dist: six (>=1.10.0)
